cli_test_framework/__init__.py
cli_test_framework/cli.py
cli_test_framework/commands/__init__.py
cli_test_framework/commands/compare.py
cli_test_framework/core/__init__.py
cli_test_framework/core/assertions.py
cli_test_framework/core/base_runner.py
cli_test_framework/core/parallel_runner.py
cli_test_framework/core/process_worker.py
cli_test_framework/core/setup.py
cli_test_framework/core/test_case.py
cli_test_framework/file_comparator/__init__.py
cli_test_framework/file_comparator/base_comparator.py
cli_test_framework/file_comparator/binary_comparator.py
cli_test_framework/file_comparator/csv_comparator.py
cli_test_framework/file_comparator/factory.py
cli_test_framework/file_comparator/h5_comparator.py
cli_test_framework/file_comparator/json_comparator.py
cli_test_framework/file_comparator/result.py
cli_test_framework/file_comparator/text_comparator.py
cli_test_framework/file_comparator/xml_comparator.py
cli_test_framework/runners/__init__.py
cli_test_framework/runners/json_runner.py
cli_test_framework/runners/parallel_json_runner.py
cli_test_framework/runners/yaml_runner.py
cli_test_framework/utils/__init__.py
cli_test_framework/utils/path_resolver.py
cli_test_framework/utils/report_generator.py
cli_test_framework-0.3.7.dist-info/METADATA
cli_test_framework-0.3.7.dist-info/WHEEL
cli_test_framework-0.3.7.dist-info/entry_points.txt
cli_test_framework-0.3.7.dist-info/top_level.txt
cli_test_framework-0.3.7.dist-info/RECORD
