Metadata-Version: 2.4
Name: cli-test-framework
Version: 0.3.7
Summary: A powerful command line testing framework in Python with setup modules, parallel execution, and file comparison capabilities.
Home-page: https://github.com/ozil111/cli-test-framework
Author: Xiaotong Wang
Author-email: xiaotongwang98@gmail.com
Project-URL: Documentation, https://github.com/ozil111/cli-test-framework/blob/main/docs/user_manual.md
Project-URL: Source, https://github.com/ozil111/cli-test-framework
Project-URL: Tracker, https://github.com/ozil111/cli-test-framework/issues
Classifier: Programming Language :: Python :: 3
Classifier: License :: OSI Approved :: MIT License
Classifier: Operating System :: OS Independent
Classifier: Development Status :: 4 - Beta
Classifier: Intended Audience :: Developers
Classifier: Topic :: Software Development :: Testing
Classifier: Topic :: Software Development :: Libraries :: Python Modules
Requires-Python: >=3.9
Requires-Dist: dukpy==0.5.0
Requires-Dist: h5py>=3.8.0
Requires-Dist: numpy>=2.0.1
Requires-Dist: setuptools>=75.8.0
Requires-Dist: wheel>=0.45.1
Dynamic: author
Dynamic: author-email
Dynamic: classifier
Dynamic: description
Dynamic: description-content-type
Dynamic: home-page
Dynamic: project-url
Dynamic: requires-dist
Dynamic: requires-python
Dynamic: summary
